fhirstarter/__init__.py
fhirstarter/errors.py
fhirstarter/examples/__init__.py
fhirstarter/examples/config.toml
fhirstarter/examples/example.py
fhirstarter/exceptions.py
fhirstarter/fhir_specification/__init__.py
fhirstarter/fhir_specification/scripts/create_sequence_data.py
fhirstarter/fhir_specification/sequences/R4B/__init__.py
fhirstarter/fhir_specification/sequences/R4B/examples.zip
fhirstarter/fhir_specification/sequences/R4B/extra-search-parameters.json
fhirstarter/fhir_specification/sequences/R4B/resource_types.json
fhirstarter/fhir_specification/sequences/R4B/search-parameters.zip
fhirstarter/fhir_specification/sequences/R5/__init__.py
fhirstarter/fhir_specification/sequences/R5/examples.zip
fhirstarter/fhir_specification/sequences/R5/extra-search-parameters.json
fhirstarter/fhir_specification/sequences/R5/resource_types.json
fhirstarter/fhir_specification/sequences/R5/search-parameters.zip
fhirstarter/fhir_specification/sequences/STU3/__init__.py
fhirstarter/fhir_specification/sequences/STU3/examples.zip
fhirstarter/fhir_specification/sequences/STU3/extra-search-parameters.json
fhirstarter/fhir_specification/sequences/STU3/resource_types.json
fhirstarter/fhir_specification/sequences/STU3/search-parameters.zip
fhirstarter/fhir_specification/sequences/__init__.py
fhirstarter/fhir_specification/utils.py
fhirstarter/fhirstarter.py
fhirstarter/functions.py
fhirstarter/interactions.py
fhirstarter/json_patch.py
fhirstarter/openapi.py
fhirstarter/providers.py
fhirstarter/resources.py
fhirstarter/search_parameters.py
fhirstarter/testclient.py
fhirstarter/tests/__init__.py
fhirstarter/tests/config.py
fhirstarter/tests/conftest.py
fhirstarter/tests/resources.py
fhirstarter/tests/test_capability_statement.py
fhirstarter/tests/test_dependencies.py
fhirstarter/tests/test_errors.py
fhirstarter/tests/test_interactions.py
fhirstarter/tests/test_openapi.py
fhirstarter/tests/test_utils.py
fhirstarter/tests/utils.py
fhirstarter/utils.py
fhirstarter-3.0.0.dist-info/LICENSE.md
fhirstarter-3.0.0.dist-info/METADATA
fhirstarter-3.0.0.dist-info/WHEEL
fhirstarter-3.0.0.dist-info/RECORD
