Metadata-Version: 2.3
Name: fhirstarter
Version: 3.0.0
Summary: An ASGI FHIR API framework built on top of FastAPI and FHIR Resources
Keywords: fhir,api,server,resources,framework,fastapi,healthcare,hl7
Author: Christopher Sande
Author-email: christopher.sande@canvasmedical.com
Maintainer: Canvas Medical Engineering
Maintainer-email: engineering@canvasmedical.com
Requires-Python: >=3.8.0,<3.14.0
Classifier: Development Status :: 5 - Production/Stable
Classifier: Environment :: Web Environment
Classifier: Framework :: AsyncIO
Classifier: Framework :: FastAPI
Classifier: Intended Audience :: Developers
Classifier: Intended Audience :: Healthcare Industry
Classifier: Intended Audience :: Information Technology
Classifier: Intended Audience :: Science/Research
Classifier: License :: OSI Approved :: MIT License
Classifier: Operating System :: OS Independent
Classifier: Programming Language :: Python :: 3
Classifier: Programming Language :: Python :: 3.8
Classifier: Programming Language :: Python :: 3.9
Classifier: Programming Language :: Python :: 3.10
Classifier: Programming Language :: Python :: 3.11
Classifier: Programming Language :: Python :: 3.12
Classifier: Programming Language :: Python :: 3.13
Classifier: Topic :: Internet
Classifier: Topic :: Internet :: WWW/HTTP
Classifier: Topic :: Internet :: WWW/HTTP :: HTTP Servers
Classifier: Topic :: Software Development
Classifier: Topic :: Software Development :: Libraries
Classifier: Topic :: Software Development :: Libraries :: Application Frameworks
Classifier: Topic :: Software Development :: Libraries :: Python Modules
Classifier: Typing :: Typed
Requires-Dist: asyncache (>=0.3.1,<0.4.0)
Requires-Dist: cachetools (>=5.5.1,<6.0.0)
Requires-Dist: eval-type-backport (>=0.2.2,<0.3.0)
Requires-Dist: fastapi (>=0.103.1,<0.116.0)
Requires-Dist: fhir.resources[xml] (>=8.0.0,<9.0.0)
Requires-Dist: httpx (>=0.24.1,<0.29.0)
Requires-Dist: orjson (>=3.10.3,<4.0.0)
Requires-Dist: python-multipart (>=0.0.6,<0.0.21)
Requires-Dist: tomli (>=2.0.1,<3.0.0) ; python_version < "3.11"
Requires-Dist: tzdata (>=2023.3,<2026.0) ; platform_system == "Windows"
Project-URL: Homepage, https://github.com/canvas-medical/fhirstarter
Project-URL: Repository, https://github.com/canvas-medical/fhirstarter
